macro.v
// Define a macro `power_of_two` that takes an input `x` and returns the value of 2 raised to the power of `x`
// This is achieved by performing a left shift operation on the binary value of 1 by `x` places
// which effectively multiplies it by 2^x.
//`define power_of_two(x) (1<<2)

// Define a macro `WORD_LEN` and set it to 32
`define WORD_LEN 32//`power_of_two(5)

// Define a macro `ADDR_BITS` and set it to 7
`define ADDR_BITS  7

// Define a macro `MATRIX_DIM` and set it to 8 by calling the `power_of_two` macro with an input of 3
`define MATRIX_DIM  8//`power_of_two(3)

`define NULL 0

Mem_Manager.v
module Mem_Manager
(
    input clk,
    input rst,
	output reg [2:0] Dir_M1,
    output reg [6:0] Dir_M2
    
);

reg [6:0] count;

always @(posedge clk or negedge rst) 
begin
    if (!rst) 
    begin
        count <= 7'd0;
        Dir_M1 <= 3'd0;
    end 
    else if (count == 7'd64) 
    begin
        count <= 7'd0;
        Dir_M2 <= 7'd0;
        if (Dir_M1 == 3'd7) 
        begin
            Dir_M1 <= 3'd0;
        end 
        else 
        begin
            Dir_M1 <= Dir_M1 + 1'd1;
        end
    end 
    else 
    begin
        count <= count + 1'd1;
        Dir_M2 <= count;
    end
end
  
endmodule

Mem_manager_tb.v
`include "macro.v"
`timescale 10ns / 1ns

module Mem_manager_tb();

    reg clk_tb;
    reg rst_tb;
    wire [(`ADDR_BITS - 1):0] Dir_M1_tb;
    wire [(`ADDR_BITS - 1):0] Dir_M2_tb;

    Mem_Manager DUT (
        .clk(clk_tb),
        .rst(rst_tb),
        .Dir_M1(Dir_M1_tb),
        .Dir_M2(Dir_M2_tb)
    );

    initial begin
        $dumpfile("test.vcd");
        $dumpvars(0, Dir_M1_tb);
        $dumpvars(1, Dir_M2_tb);

        clk_tb = 0;

        rst_tb = 1;
		  
        #10
        rst_tb = 0;
        #10
        rst_tb = 1;
        #1000;

        // Test case 1
        #100;
        #1000;
        $finish;
    end

    always #5 clk_tb = ~clk_tb;

endmodule

test.vcd
$date
	Tue Apr 18 23:33:49 2023
$end
$version
	Icarus Verilog
$end
$timescale
	1ns
$end
$scope module Mem_manager_tb $end
$var wire 7 ! Dir_M1_tb [6:0] $end
$upscope $end
$scope module Mem_manager_tb $end
$var wire 7 " Dir_M2_tb [6:0] $end
$upscope $end
$enddefinitions $end
#0
$dumpvars
bx "
bx !
$end
#100
b0 "
b0 !
#250
b1000 "
#350
b10000 "
#450
b11000 "
#550
b100000 "
#650
b101000 "
#750
b110000 "
#850
b111000 "
#950
b1000 !
b0 "
#1050
b1000 "
#1150
b10000 "
#1250
b11000 "
#1350
b100000 "
#1450
b101000 "
#1550
b110000 "
#1650
b111000 "
#1750
b10000 !
b0 "
#1850
b1000 "
#1950
b10000 "
#2050
b11000 "
#2150
b100000 "
#2250
b101000 "
#2350
b110000 "
#2450
b111000 "
#2550
b11000 !
b0 "
#2650
b1000 "
#2750
b10000 "
#2850
b11000 "
#2950
b100000 "
#3050
b101000 "
#3150
b110000 "
#3250
b111000 "
#3350
b100000 !
b0 "
#3450
b1000 "
#3550
b10000 "
#3650
b11000 "
#3750
b100000 "
#3850
b101000 "
#3950
b110000 "
#4050
b111000 "
#4150
b101000 !
b0 "
#4250
b1000 "
#4350
b10000 "
#4450
b11000 "
#4550
b100000 "
#4650
b101000 "
#4750
b110000 "
#4850
b111000 "
#4950
b110000 !
b0 "
#5050
b1000 "
#5150
b10000 "
#5250
b11000 "
#5350
b100000 "
#5450
b101000 "
#5550
b110000 "
#5650
b111000 "
#5750
b111000 !
b0 "
#5850
b1000 "
#5950
b10000 "
#6050
b11000 "
#6150
b100000 "
#6250
b101000 "
#6350
b110000 "
#6450
b111000 "
#6550
b0 !
b0 "
#6650
b1000 "
#6750
b10000 "
#6850
b11000 "
#6950
b100000 "
#7050
b101000 "
#7150
b110000 "
#7250
b111000 "
#7350
b1000 !
b0 "
#7450
b1000 "
#7550
b10000 "
#7650
b11000 "
#7750
b100000 "
#7850
b101000 "
#7950
b110000 "
#8050
b111000 "
#8150
b10000 !
b0 "
#8250
b1000 "
#8350
b10000 "
#8450
b11000 "
#8550
b100000 "
#8650
b101000 "
#8750
b110000 "
#8850
b111000 "
#8950
b11000 !
b0 "
#9050
b1000 "
#9150
b10000 "
#9250
b11000 "
#9350
b100000 "
#9450
b101000 "
#9550
b110000 "
#9650
b111000 "
#9750
b100000 !
b0 "
#9850
b1000 "
#9950
b10000 "
#10050
b11000 "
#10150
b100000 "
#10250
b101000 "
#10350
b110000 "
#10450
b111000 "
#10550
b101000 !
b0 "
#10650
b1000 "
#10750
b10000 "
#10850
b11000 "
#10950
b100000 "
#11050
b101000 "
#11150
b110000 "
#11250
b111000 "
#11350
b110000 !
b0 "
#11450
b1000 "
#11550
b10000 "
#11650
b11000 "
#11750
b100000 "
#11850
b101000 "
#11950
b110000 "
#12050
b111000 "
#12150
b111000 !
b0 "
#12250
b1000 "
#12350
b10000 "
#12450
b11000 "
#12550
b100000 "
#12650
b101000 "
#12750
b110000 "
#12850
b111000 "
#12950
b0 !
b0 "
#13050
b1000 "
#13150
b10000 "
#13250
b11000 "
#13350
b100000 "
#13450
b101000 "
#13550
b110000 "
#13650
b111000 "
#13750
b1000 !
b0 "
#13850
b1000 "
#13950
b10000 "
#14050
b11000 "
#14150
b100000 "
#14250
b101000 "
#14350
b110000 "
#14450
b111000 "
#14550
b10000 !
b0 "
#14650
b1000 "
#14750
b10000 "
#14850
b11000 "
#14950
b100000 "
#15050
b101000 "
#15150
b110000 "
#15250
b111000 "
#15350
b11000 !
b0 "
#15450
b1000 "
#15550
b10000 "
#15650
b11000 "
#15750
b100000 "
#15850
b101000 "
#15950
b110000 "
#16050
b111000 "
#16150
b100000 !
b0 "
#16250
b1000 "
#16350
b10000 "
#16450
b11000 "
#16550
b100000 "
#16650
b101000 "
#16750
b110000 "
#16850
b111000 "
#16950
b101000 !
b0 "
#17050
b1000 "
#17150
b10000 "
#17250
b11000 "
#17350
b100000 "
#17450
b101000 "
#17550
b110000 "
#17650
b111000 "
#17750
b110000 !
b0 "
#17850
b1000 "
#17950
b10000 "
#18050
b11000 "
#18150
b100000 "
#18250
b101000 "
#18350
b110000 "
#18450
b111000 "
#18550
b111000 !
b0 "
#18650
b1000 "
#18750
b10000 "
#18850
b11000 "
#18950
b100000 "
#19050
b101000 "
#19150
b110000 "
#19250
b111000 "
#19350
b0 !
b0 "
#19450
b1000 "
#19550
b10000 "
#19650
b11000 "
#19750
b100000 "
#19850
b101000 "
#19950
b110000 "
#20050
b111000 "
#20150
b1000 !
b0 "
#20250
b1000 "
#20350
b10000 "
#20450
b11000 "
#20550
b100000 "
#20650
b101000 "
#20750
b110000 "
#20850
b111000 "
#20950
b10000 !
b0 "
#21050
b1000 "
#21150
b10000 "
